CHANGES.rst
LICENSE.txt
MANIFEST.in
README.rst
dev_requirements.txt
setup.cfg
setup.py
bin/__init__.py
bin/eb_completion.bash
bin/install-ebcli.py
ebcli/__init__.py
ebcli/bundled/__init__.py
ebcli/bundled/_compose/__init__.py
ebcli/bundled/_compose/config.py
ebcli/bundled/_compose/container.py
ebcli/bundled/_compose/progress_stream.py
ebcli/bundled/_compose/project.py
ebcli/bundled/_compose/service.py
ebcli/bundled/_compose/cli/__init__.py
ebcli/bundled/_compose/cli/colors.py
ebcli/bundled/_compose/cli/command.py
ebcli/bundled/_compose/cli/docker_client.py
ebcli/bundled/_compose/cli/docopt_command.py
ebcli/bundled/_compose/cli/errors.py
ebcli/bundled/_compose/cli/formatter.py
ebcli/bundled/_compose/cli/log_printer.py
ebcli/bundled/_compose/cli/main.py
ebcli/bundled/_compose/cli/multiplexer.py
ebcli/bundled/_compose/cli/utils.py
ebcli/bundled/_compose/cli/verbose_proxy.py
ebcli/containers/__init__.py
ebcli/containers/abstractcontainer.py
ebcli/containers/commands.py
ebcli/containers/compat.py
ebcli/containers/compose.py
ebcli/containers/container_viewmodel.py
ebcli/containers/containerops.py
ebcli/containers/dockerrun.py
ebcli/containers/envvarcollector.py
ebcli/containers/factory.py
ebcli/containers/fshandler.py
ebcli/containers/generic_container.py
ebcli/containers/log.py
ebcli/containers/multicontainer.py
ebcli/containers/pathconfig.py
ebcli/containers/preconfigured_container.py
ebcli/containers/containerfiles/container_config.json
ebcli/containers/containerfiles/glassfish-runtime-4.0-jdk7
ebcli/containers/containerfiles/glassfish-runtime-4.1-jdk8
ebcli/containers/containerfiles/golang-runtime-1.3
ebcli/containers/containerfiles/golang-runtime-1.4
ebcli/containers/containerfiles/python3-runtime
ebcli/controllers/__init__.py
ebcli/controllers/abort.py
ebcli/controllers/clone.py
ebcli/controllers/config.py
ebcli/controllers/console.py
ebcli/controllers/create.py
ebcli/controllers/deploy.py
ebcli/controllers/events.py
ebcli/controllers/health.py
synctree_awsebcli.egg-info/PKG-INFO
synctree_awsebcli.egg-info/SOURCES.txt
synctree_awsebcli.egg-info/dependency_links.txt
synctree_awsebcli.egg-info/entry_points.txt
synctree_awsebcli.egg-info/requires.txt
synctree_awsebcli.egg-info/top_level.txt