Metadata-Version: 1.1
Name: synctree-awsebcli
Version: 3.5.2
Summary: Command Line Interface for AWS EB.
Home-page: http://aws.amazon.com/elasticbeanstalk/
Author: Nick Humrich
Author-email: humrichn@amazon.com
License: Apache License 2.0
Platform: UNKNOWN
Classifier: Development Status :: 5 - Production/Stable
Classifier: Intended Audience :: Developers
Classifier: Intended Audience :: System Administrators
Classifier: Natural Language :: English
Classifier: License :: OSI Approved :: Apache Software License
Classifier: Programming Language :: Python
Classifier: Programming Language :: Python :: 2.7
Classifier: Programming Language :: Python :: 3
Classifier: Programming Language :: Python :: 3.4
